fondat/salesforce/__init__.py
fondat/salesforce/bulk.py
fondat/salesforce/client.py
fondat/salesforce/jobs.py
fondat/salesforce/limits.py
fondat/salesforce/oauth.py
fondat/salesforce/service.py
fondat/salesforce/sobjects.py
fondat_salesforce-4.1.0.dist-info/LICENSE
fondat_salesforce-4.1.0.dist-info/METADATA
fondat_salesforce-4.1.0.dist-info/WHEEL
fondat_salesforce-4.1.0.dist-info/RECORD
