Metadata-Version: 2.1
Name: fondat-salesforce
Version: 4.1.0
Summary: Fondat package for Salesforce.
Home-page: https://github.com/fondat/fondat-salesforce/
License: MIT
Keywords: asgi,framework,resource,openapi
Author: fondat-salesforce authors
Requires-Python: >=3.10,<4.0
Classifier: Development Status :: 5 - Production/Stable
Classifier: Intended Audience :: Developers
Classifier: License :: OSI Approved :: MIT License
Classifier: Programming Language :: Python :: 3
Classifier: Programming Language :: Python :: 3.10
Classifier: Programming Language :: Python :: 3.11
Classifier: Topic :: Software Development :: Libraries :: Application Frameworks
Requires-Dist: aiohttp (>=3.8,<4.0)
Requires-Dist: fondat (>=4.1,<5.0)
Project-URL: Documentation, https://github.com/fondat/fondat-salesforce/wiki
